pdbsearch/__init__.py
pdbsearch/__main__.py
pdbsearch/models.py
pdbsearch/nodes.py
pdbsearch/queries.py
pdbsearch/schema.py
pdbsearch/search.py
pdbsearch/terms.py
pdbsearch-0.5.0.dist-info/licenses/LICENSE
pdbsearch-0.5.0.dist-info/METADATA
pdbsearch-0.5.0.dist-info/WHEEL
pdbsearch-0.5.0.dist-info/entry_points.txt
pdbsearch-0.5.0.dist-info/top_level.txt
pdbsearch-0.5.0.dist-info/RECORD
